{
   "kind": "collectionType",
   "collectionName": "pages",
   "info": {
      "singularName": "page",
      "pluralName": "pages",
      "displayName": "Page",
      "description": ""
   },
   "options": {
      "draftAndPublish": true
   },
   "pluginOptions": {
      "i18n": {
         "localized": true
      }
   },
   "attributes": {
      "path": {
         "pluginOptions": {
            "i18n": {
               "localized": true
            }
         },
         "type": "string",
         "unique": true,
         "required": true
      },
      "title": {
         "pluginOptions": {
            "i18n": {
               "localized": true
            }
         },
         "type": "string",
         "required": true
      },
      "metaTitle": {
         "pluginOptions": {
            "i18n": {
               "localized": true
            }
         },
         "type": "string"
      },
      "metaDescription": {
         "pluginOptions": {
            "i18n": {
               "localized": true
            }
         },
         "type": "text"
      },
      "sections": {
         "pluginOptions": {
            "i18n": {
               "localized": true
            }
         },
         "type": "dynamiczone",
         "components": [
            "page.hero",
            "page.browse",
            "page.stats",
            "page.split-with-image",
            "page.press",
            "section.featured-products",
            "section.social-gallery",
            "section.lifetime-warranty",
            "section.banner",
            "section.quote-gallery"
         ],
         "required": true
      }
   }
}
